{
  "feature": [
    {
      "domain": {
        "floats": {}
      },
      "fixedShape": {
        "axis": []
      },
      "name": "activity",
      "parsingOptions": {
        "tfOptions": {
          "fixedLenFeature": {}
        }
      },
      "type": "FLOAT"
    },
    {
      "domain": {
        "floats": {}
      },
      "fixedShape": {
        "axis": []
      },
      "name": "age",
      "parsingOptions": {
        "tfOptions": {
          "fixedLenFeature": {}
        }
      },
      "type": "FLOAT"
    },
    {
      "domain": {
        "floats": {}
      },
      "fixedShape": {
        "axis": []
      },
      "name": "engagement",
      "parsingOptions": {
        "tfOptions": {
          "fixedLenFeature": {}
        }
      },
      "type": "FLOAT"
    },
    {
      "domain": {
        "floats": {}
      },
      "fixedShape": {
        "axis": []
      },
      "name": "familiarity",
      "parsingOptions": {
        "tfOptions": {
          "fixedLenFeature": {}
        }
      },
      "type": "FLOAT"
    },
    {
      "domain": {
        "ints": {
          "isCategorical": false,
          "max": "9223372036854775807",
          "min": "-9223372036854775808",
          "vocabularyFile": ""
        }
      },
      "fixedShape": {
        "axis": []
      },
      "name": "hallelujah_reaction",
      "parsingOptions": {
        "tfOptions": {
          "fixedLenFeature": {}
        }
      },
      "type": "INT"
    },
    {
      "domain": {
        "ints": {
          "isCategorical": false,
          "max": "9223372036854775807",
          "min": "-9223372036854775808",
          "vocabularyFile": ""
        }
      },
      "fixedShape": {
        "axis": []
      },
      "name": "hearing_impairments",
      "parsingOptions": {
        "tfOptions": {
          "fixedLenFeature": {}
        }
      },
      "type": "INT"
    },
    {
      "domain": {
        "strings": {}
      },
      "fixedShape": {
        "axis": []
      },
      "name": "language",
      "parsingOptions": {
        "tfOptions": {
          "fixedLenFeature": {}
        }
      },
      "type": "BYTES"
    },
    {
      "domain": {
        "floats": {}
      },
      "fixedShape": {
        "axis": []
      },
      "name": "like_dislike",
      "parsingOptions": {
        "tfOptions": {
          "fixedLenFeature": {}
        }
      },
      "type": "FLOAT"
    },
    {
      "domain": {
        "strings": {}
      },
      "fixedShape": {
        "axis": []
      },
      "name": "location",
      "parsingOptions": {
        "tfOptions": {
          "fixedLenFeature": {}
        }
      },
      "type": "BYTES"
    },
    {
      "domain": {
        "strings": {}
      },
      "fixedShape": {
        "axis": []
      },
      "name": "nationality",
      "parsingOptions": {
        "tfOptions": {
          "fixedLenFeature": {}
        }
      },
      "type": "BYTES"
    },
    {
      "domain": {
        "floats": {}
      },
      "fixedShape": {
        "axis": []
      },
      "name": "positivity",
      "parsingOptions": {
        "tfOptions": {
          "fixedLenFeature": {}
        }
      },
      "type": "FLOAT"
    },
    {
      "domain": {
        "strings": {}
      },
      "fixedShape": {
        "axis": []
      },
      "name": "sex",
      "parsingOptions": {
        "tfOptions": {
          "fixedLenFeature": {}
        }
      },
      "type": "BYTES"
    },
    {
      "domain": {
        "floats": {}
      },
      "fixedShape": {
        "axis": []
      },
      "name": "tension",
      "parsingOptions": {
        "tfOptions": {
          "fixedLenFeature": {}
        }
      },
      "type": "FLOAT"
    }
  ],
  "sparseFeature": []
}